unified_signals/__init__.py
unified_signals/exceptions.py
unified_signals/signals.py
django_unified_signals-0.2.1.dist-info/LICENSE
django_unified_signals-0.2.1.dist-info/METADATA
django_unified_signals-0.2.1.dist-info/WHEEL
django_unified_signals-0.2.1.dist-info/RECORD
